liquid_plotly/Accordion.py
liquid_plotly/AccordionPanel.py
liquid_plotly/AccordionSection.py
liquid_plotly/AccordionToggle.py
liquid_plotly/Badge.py
liquid_plotly/BgCells.py
liquid_plotly/Breadcrumbs.py
liquid_plotly/Button.py
liquid_plotly/Card.py
liquid_plotly/CardStack.py
liquid_plotly/Checkbox.py
liquid_plotly/CircularProgress.py
liquid_plotly/Crumb.py
liquid_plotly/Header.py
liquid_plotly/Icon.py
liquid_plotly/Input.py
liquid_plotly/InputMessage.py
liquid_plotly/Label.py
liquid_plotly/Link.py
liquid_plotly/Loading.py
liquid_plotly/Modal.py
liquid_plotly/Notice.py
liquid_plotly/Notification.py
liquid_plotly/Option.py
liquid_plotly/Pagination.py
liquid_plotly/Progress.py
liquid_plotly/Radio.py
liquid_plotly/Select.py
liquid_plotly/Slider.py
liquid_plotly/SrLive.py
liquid_plotly/SrOnly.py
liquid_plotly/Step.py
liquid_plotly/Stepper.py
liquid_plotly/Switch.py
liquid_plotly/SwitchItem.py
liquid_plotly/Tab.py
liquid_plotly/Table.py
liquid_plotly/TableBody.py
liquid_plotly/TableCaption.py
liquid_plotly/TableCell.py
liquid_plotly/TableCol.py
liquid_plotly/TableColgroup.py
liquid_plotly/TableFoot.py
liquid_plotly/TableHead.py
liquid_plotly/TableHeader.py
liquid_plotly/TableRow.py
liquid_plotly/TableToolbar.py
liquid_plotly/Tablist.py
liquid_plotly/Tabpanel.py
liquid_plotly/Tabpanellist.py
liquid_plotly/Tabs.py
liquid_plotly/Toggle.py
liquid_plotly/Tooltip.py
liquid_plotly/Typo.py
liquid_plotly/__init__.py
liquid_plotly/_imports_.py
liquid_plotly/liquid_plotly.umd.js
liquid_plotly/metadata.json
liquid_plotly/package-info.json
liquid_plotly/style.css
liquid_plotly/assets/3d.svg
liquid_plotly/assets/add.svg
liquid_plotly/assets/arrow-double-left.svg
liquid_plotly/assets/arrow-double-right.svg
liquid_plotly/assets/arrow-down.svg
liquid_plotly/assets/arrow-left.svg
liquid_plotly/assets/arrow-right.svg
liquid_plotly/assets/arrow-up-n-down.svg
liquid_plotly/assets/arrow-up.svg
liquid_plotly/assets/atom.svg
liquid_plotly/assets/attention.svg
liquid_plotly/assets/audio.svg
liquid_plotly-0.0.1.dist-info/LICENSE.md
liquid_plotly-0.0.1.dist-info/METADATA
liquid_plotly-0.0.1.dist-info/WHEEL
liquid_plotly-0.0.1.dist-info/top_level.txt
liquid_plotly-0.0.1.dist-info/RECORD
