Metadata-Version: 2.1
Name: liquid_plotly
Version: 0.0.1
Summary: Liquid for Plotly
Home-page: UNKNOWN
Author: User Experience Strategy & Design unit, part of the Chief Digital Organization at EMD Group <liquid@emdgroup.com> (https://github.com/emdgroup-liquid)
License: SEE LICENSE IN LICENSE.md
Platform: UNKNOWN
Classifier: Framework :: Dash
License-File: LICENSE.md
